brokerio/__about__.py
brokerio/__init__.py
brokerio/__main__.py
brokerio/app.py
brokerio/config.yaml
brokerio/cli/CLI.py
brokerio/cli/__init__.py
brokerio/cli/interfaces/BrokerCLI.py
brokerio/cli/interfaces/GuardCLI.py
brokerio/cli/interfaces/SkillsCLI.py
brokerio/cli/interfaces/__init__.py
brokerio/client/Client.py
brokerio/client/__init__.py
brokerio/client/utils.py
brokerio/db/Database.py
brokerio/db/__init__.py
brokerio/db/collection/Clients.py
brokerio/db/collection/Roles.py
brokerio/db/collection/Skills.py
brokerio/db/collection/Tasks.py
brokerio/db/collection/Users.py
brokerio/db/collection/__init__.py
brokerio/db/utils/__init__.py
brokerio/guard/Guard.py
brokerio/guard/__init__.py
brokerio/skills/SkillModel.py
brokerio/skills/__init__.py
brokerio/skills/models/__init__.py
brokerio/skills/models/azure/Dockerfile
brokerio/skills/models/azure/Model.py
brokerio/skills/models/azure/Skill.py
brokerio/skills/models/azure/__init__.py
brokerio/skills/models/azure/config.yaml
brokerio/skills/models/hf_pipeline/Dockerfile
brokerio/skills/models/hf_pipeline/Model.py
brokerio/skills/models/hf_pipeline/Skill.py
brokerio/skills/models/hf_pipeline/__init__.py
brokerio/skills/models/hf_pipeline/config.yaml
brokerio/skills/models/hf_pipeline/tasks/__init__.py
brokerio/skills/models/hf_pipeline/tasks/fill-mask.yaml
brokerio/skills/models/hf_pipeline/tasks/question-answering.yaml
brokerio/skills/models/hf_pipeline/tasks/summarization.yaml
brokerio/skills/models/hf_pipeline/tasks/text-classification.yaml
brokerio/skills/models/hf_pipeline/tasks/text-generation.yaml
brokerio/skills/models/hf_pipeline/tasks/text2text.yaml
brokerio/skills/models/hf_pipeline/tasks/token-classification.yaml
brokerio/skills/models/hf_pipeline/tasks/translation_en_to_de.yaml
brokerio/skills/models/llama_cpp/Dockerfile
brokerio/skills/models/llama_cpp/Model.py
brokerio/skills/models/llama_cpp/Skill.py
brokerio/skills/models/llama_cpp/__init__.py
brokerio/skills/models/llama_cpp/config.yaml
brokerio-0.5.1.dist-info/licenses/LICENSE
brokerio-0.5.1.dist-info/licenses/NOTICE
brokerio-0.5.1.dist-info/METADATA
brokerio-0.5.1.dist-info/WHEEL
brokerio-0.5.1.dist-info/entry_points.txt
brokerio-0.5.1.dist-info/top_level.txt
brokerio-0.5.1.dist-info/RECORD
