Metadata-Version: 2.4
Name: BrokerIO
Version: 0.5.1
Summary: A broker for routing tasks to different services
Home-page: https://github.com/UKPLab/CARE_broker
Author: Ubiquitous Knowledge Processing (UKP) Lab
Author-email: dennis.zyska@tu-darmstadt.de
Project-URL: Bug Tracker, https://github.com/UKPLab/CARE_broker/issues
Classifier: Programming Language :: Python :: 3
Classifier: License :: OSI Approved :: Apache Software License
Classifier: Operating System :: OS Independent
Requires-Python: >=3.12
License-File: LICENSE
License-File: NOTICE
Requires-Dist: aiohttp>=3.10.5
Requires-Dist: redis>=5.0.8
Requires-Dist: python-socketio>=5.11.4
Requires-Dist: python-socketio[client]>=5.11.4
Requires-Dist: pyyaml>=6.0.2
Requires-Dist: python-arango>=8.1.0
Requires-Dist: pycryptodome>=3.20.0
Requires-Dist: urllib3>=2.2.2
Requires-Dist: numpy>=2.1.1
Requires-Dist: psutil>=6.0.0
Provides-Extra: skills
Requires-Dist: docker>=7.1.0; extra == "skills"
Dynamic: license-file
